range_merge/__init__.py
range_merge/__init__.pyi
range_merge/py.typed
range_merge-0.1.0.dist-info/licenses/LICENSE
range_merge-0.1.0.dist-info/WHEEL
range_merge-0.1.0.dist-info/METADATA
range_merge-0.1.0.dist-info/RECORD
