Metadata-Version: 2.4
Name: range-merge
Version: 0.1.0
Summary: Merge ranges of numbers/IP addresses
Keywords: range,merge,interval,overlap,ip-address
Author: Joelle Maslak
Author-email: Joelle Maslak <jmaslak@antelope.net>
License-Expression: BSD-2-Clause
License-File: LICENSE
Classifier: Development Status :: 4 - Beta
Classifier: Intended Audience :: Developers
Classifier: License :: OSI Approved :: BSD License
Classifier: Operating System :: OS Independent
Classifier: Programming Language :: Python :: 3
Classifier: Programming Language :: Python :: 3.10
Classifier: Programming Language :: Python :: 3.11
Classifier: Programming Language :: Python :: 3.12
Classifier: Programming Language :: Python :: 3.13
Classifier: Topic :: Software Development :: Libraries :: Python Modules
Classifier: Topic :: Utilities
Classifier: Typing :: Typed
Requires-Python: >=3.10
Project-URL: Homepage, https://github.com/antelope/range_merge
Project-URL: Issues, https://github.com/antelope/range_merge/issues
Project-URL: Repository, https://github.com/antelope/range_merge
